README.md
setup.py
simple_roaming_certificate/__init__.py
simple_roaming_certificate/utils.py
simple_roaming_certificate.egg-info/PKG-INFO
simple_roaming_certificate.egg-info/SOURCES.txt
simple_roaming_certificate.egg-info/dependency_links.txt
simple_roaming_certificate.egg-info/requires.txt
simple_roaming_certificate.egg-info/top_level.txt