Metadata-Version: 2.1
Name: simple-roaming-certificate
Version: 1.3
Summary: Simple certificate generator
Home-page: UNKNOWN
Author: Mike Richardson
Author-email: doctor@perpetual.name
License: UNKNOWN
Platform: UNKNOWN
Classifier: Programming Language :: Python :: 2
Classifier: License :: OSI Approved :: MIT License
Classifier: Operating System :: OS Independent
